[
    {
        "kind": "Listing",
        "data": {
            "after": null,
            "dist": 1,
            "modhash": "",
            "geo_filter": "",
            "children": [
                {
                    "kind": "t3",
                    "data": {
                        "approved_at_utc": null,
                        "subreddit": "FredditFreebuild",
                        "selftext": "STOP. chris has apologized for the things he has done, All these things you have said to him is hurtful. He is a fucking person too and so are you. What if someone or your friend comes up to you and says your a fag or a dickhead? Would that make you sad? Yes, and the things  you guys have said to Chris made him sad. He has anger issues like me, does that make ME a dickhead? And you are all probably going to reply with \"yeah but Chris is always salty and a dickweed \" fucking so? That's him, he is his own person, he has anger issues, you are not in Chris's life. He's sorry okay? So just stop it. ",
                        "user_reports": [],
                        "saved": false,
                        "mod_reason_title": null,
                        "gilded": 0,
                        "clicked": false,
                        "title": "A word to everyone who hates Chris",
                        "link_flair_richtext": [],
                        "subreddit_name_prefixed": "r/FredditFreebuild",
                        "hidden": false,
                        "pwls": null,
                        "link_flair_css_class": null,
                        "downs": 0,
                        "thumbnail_height": null,
                        "top_awarded_type": null,
                        "parent_whitelist_status": null,
                        "hide_score": false,
                        "name": "t3_3i7e24",
                        "quarantine": false,
                        "link_flair_text_color": "dark",
                        "upvote_ratio": 0.86,
                        "author_flair_background_color": "",
                        "subreddit_type": "public",
                        "ups": 5,
                        "total_awards_received": 0,
                        "media_embed": {},
                        "thumbnail_width": null,
                        "author_flair_template_id": null,
                        "is_original_content": false,
                        "author_fullname": "t2_jy86i",
                        "secure_media": null,
                        "is_reddit_media_domain": false,
                        "is_meta": false,
                        "category": null,
                        "secure_media_embed": {},
                        "link_flair_text": null,
                        "can_mod_post": false,
                        "score": 5,
                        "approved_by": null,
                        "is_created_from_ads_ui": false,
                        "author_premium": false,
                        "thumbnail": "self",
                        "edited": false,
                        "author_flair_css_class": null,
                        "author_flair_richtext": [],
                        "gildings": {},
                        "content_categories": null,
                        "is_self": true,
                        "mod_note": null,
                        "created": 1440426339.0,
                        "link_flair_type": "text",
                        "wls": null,
                        "removed_by_category": null,
                        "banned_by": null,
                        "author_flair_type": "text",
                        "domain": "self.FredditFreebuild",
                        "allow_live_comments": false,
                        "selftext_html": "&lt;!-- SC_OFF --&gt;&lt;div class=\"md\"&gt;&lt;p&gt;STOP. chris has apologized for the things he has done, All these things you have said to him is hurtful. He is a fucking person too and so are you. What if someone or your friend comes up to you and says your a fag or a dickhead? Would that make you sad? Yes, and the things  you guys have said to Chris made him sad. He has anger issues like me, does that make ME a dickhead? And you are all probably going to reply with &amp;quot;yeah but Chris is always salty and a dickweed &amp;quot; fucking so? That&amp;#39;s him, he is his own person, he has anger issues, you are not in Chris&amp;#39;s life. He&amp;#39;s sorry okay? So just stop it. &lt;/p&gt;\n&lt;/div&gt;&lt;!-- SC_ON --&gt;",
                        "likes": null,
                        "suggested_sort": null,
                        "banned_at_utc": null,
                        "view_count": null,
                        "archived": false,
                        "no_follow": false,
                        "is_crosspostable": false,
                        "pinned": false,
                        "over_18": false,
                        "all_awardings": [],
                        "awarders": [],
                        "media_only": false,
                        "can_gild": false,
                        "spoiler": false,
                        "locked": false,
                        "author_flair_text": "Skool Sux",
                        "treatment_tags": [],
                        "visited": false,
                        "removed_by": null,
                        "num_reports": null,
                        "distinguished": null,
                        "subreddit_id": "t5_39dhr",
                        "author_is_blocked": false,
                        "mod_reason_by": null,
                        "removal_reason": null,
                        "link_flair_background_color": "",
                        "id": "3i7e24",
                        "is_robot_indexable": true,
                        "num_duplicates": 0,
                        "report_reasons": null,
                        "author": "NathanFazbear",
                        "discussion_type": null,
                        "num_comments": 6,
                        "send_replies": true,
                        "media": null,
                        "contest_mode": false,
                        "author_patreon_flair": false,
                        "author_flair_text_color": "dark",
                        "permalink": "/r/FredditFreebuild/comments/3i7e24/a_word_to_everyone_who_hates_chris/",
                        "whitelist_status": null,
                        "stickied": false,
                        "url": "https://old.reddit.com/r/FredditFreebuild/comments/3i7e24/a_word_to_everyone_who_hates_chris/",
                        "subreddit_subscribers": 57,
                        "created_utc": 1440426339.0,
                        "num_crossposts": 0,
                        "mod_reports": [],
                        "is_video": false
                    }
                }
            ],
            "before": null
        }
    },
    {
        "kind": "Listing",
        "data": {
            "after": null,
            "dist": null,
            "modhash": "",
            "geo_filter": "",
            "children": [
                {
                    "kind": "t1",
                    "data": {
                        "total_awards_received": 0,
                        "approved_at_utc": null,
                        "author_is_blocked": false,
                        "comment_type": null,
                        "awarders": [],
                        "mod_reason_by": null,
                        "banned_by": null,
                        "ups": 1,
                        "removal_reason": null,
                        "link_id": "t3_3i7e24",
                        "author_flair_template_id": null,
                        "likes": null,
                        "replies": "",
                        "user_reports": [],
                        "saved": false,
                        "id": "cuets9f",
                        "banned_at_utc": null,
                        "mod_reason_title": null,
                        "gilded": 0,
                        "archived": false,
                        "collapsed_reason_code": null,
                        "no_follow": true,
                        "author": "[deleted]",
                        "can_mod_post": false,
                        "send_replies": true,
                        "parent_id": "t3_3i7e24",
                        "score": 1,
                        "approved_by": null,
                        "report_reasons": null,
                        "all_awardings": [],
                        "subreddit_id": "t5_39dhr",
                        "body": "I looked at the title and said, this post is directed at me, but man theres a lot of things i didnt know about him, that one day when he was banned, I went full on at him, he is young and got anger issues, im sorry, I got a bit of un-normal^if^thats^a^word   anger in me so, I say\n\n\nSorry\n-Silver",
                        "edited": false,
                        "downs": 0,
                        "author_flair_css_class": null,
                        "collapsed": false,
                        "is_submitter": false,
                        "body_html": "&lt;div class=\"md\"&gt;&lt;p&gt;I looked at the title and said, this post is directed at me, but man theres a lot of things i didnt know about him, that one day when he was banned, I went full on at him, he is young and got anger issues, im sorry, I got a bit of un-normal&lt;sup&gt;if&lt;sup&gt;thats&lt;sup&gt;a&lt;sup&gt;word&lt;/sup&gt;&lt;/sup&gt;&lt;/sup&gt;&lt;/sup&gt;   anger in me so, I say&lt;/p&gt;\n\n&lt;p&gt;Sorry\n-Silver&lt;/p&gt;\n&lt;/div&gt;",
                        "gildings": {},
                        "collapsed_reason": null,
                        "associated_award": null,
                        "stickied": false,
                        "subreddit_type": "public",
                        "can_gild": false,
                        "top_awarded_type": null,
                        "unrepliable_reason": null,
                        "author_flair_text_color": "dark",
                        "score_hidden": false,
                        "permalink": "/r/FredditFreebuild/comments/3i7e24/a_word_to_everyone_who_hates_chris/cuets9f/",
                        "num_reports": null,
                        "locked": false,
                        "name": "t1_cuets9f",
                        "created": 1440484243.0,
                        "subreddit": "FredditFreebuild",
                        "author_flair_text": null,
                        "treatment_tags": [],
                        "created_utc": 1440484243.0,
                        "subreddit_name_prefixed": "r/FredditFreebuild",
                        "controversiality": 0,
                        "depth": 0,
                        "author_flair_background_color": "",
                        "collapsed_because_crowd_control": null,
                        "mod_reports": [],
                        "mod_note": null,
                        "distinguished": null
                    }
                },
                {
                    "kind": "t1",
                    "data": {
                        "subreddit_id": "t5_39dhr",
                        "approved_at_utc": null,
                        "author_is_blocked": false,
                        "comment_type": null,
                        "awarders": [],
                        "mod_reason_by": null,
                        "banned_by": null,
                        "author_flair_type": "text",
                        "total_awards_received": 0,
                        "subreddit": "FredditFreebuild",
                        "author_flair_template_id": null,
                        "likes": null,
                        "replies": "",
                        "user_reports": [],
                        "saved": false,
                        "id": "cufmc6z",
                        "banned_at_utc": null,
                        "mod_reason_title": null,
                        "gilded": 0,
                        "archived": false,
                        "collapsed_reason_code": null,
                        "no_follow": true,
                        "author": "Freddy_Fuckboy",
                        "can_mod_post": false,
                        "created_utc": 1440542925.0,
                        "send_replies": true,
                        "parent_id": "t3_3i7e24",
                        "score": 1,
                        "author_fullname": "t2_mk6li",
                        "approved_by": null,
                        "mod_note": null,
                        "all_awardings": [],
                        "collapsed": false,
                        "body": "\"some things are best left forgotten, for now.\"",
                        "edited": false,
                        "top_awarded_type": null,
                        "author_flair_css_class": null,
                        "name": "t1_cufmc6z",
                        "is_submitter": false,
                        "downs": 0,
                        "author_flair_richtext": [],
                        "author_patreon_flair": false,
                        "body_html": "&lt;div class=\"md\"&gt;&lt;p&gt;&amp;quot;some things are best left forgotten, for now.&amp;quot;&lt;/p&gt;\n&lt;/div&gt;",
                        "removal_reason": null,
                        "collapsed_reason": null,
                        "distinguished": null,
                        "associated_award": null,
                        "stickied": false,
                        "author_premium": false,
                        "can_gild": false,
                        "gildings": {},
                        "unrepliable_reason": null,
                        "author_flair_text_color": null,
                        "score_hidden": false,
                        "permalink": "/r/FredditFreebuild/comments/3i7e24/a_word_to_everyone_who_hates_chris/cufmc6z/",
                        "subreddit_type": "public",
                        "locked": false,
                        "report_reasons": null,
                        "created": 1440542925.0,
                        "author_flair_text": null,
                        "treatment_tags": [],
                        "link_id": "t3_3i7e24",
                        "subreddit_name_prefixed": "r/FredditFreebuild",
                        "controversiality": 0,
                        "depth": 0,
                        "author_flair_background_color": null,
                        "collapsed_because_crowd_control": null,
                        "mod_reports": [],
                        "num_reports": null,
                        "ups": 1
                    }
                },
                {
                    "kind": "t1",
                    "data": {
                        "total_awards_received": 0,
                        "approved_at_utc": null,
                        "author_is_blocked": false,
                        "comment_type": null,
                        "awarders": [],
                        "mod_reason_by": null,
                        "banned_by": null,
                        "ups": 1,
                        "removal_reason": null,
                        "link_id": "t3_3i7e24",
                        "author_flair_template_id": null,
                        "likes": null,
                        "replies": {
                            "kind": "Listing",
                            "data": {
                                "after": null,
                                "dist": null,
                                "modhash": "",
                                "geo_filter": "",
                                "children": [
                                    {
                                        "kind": "t1",
                                        "data": {
                                            "subreddit_id": "t5_39dhr",
                                            "approved_at_utc": null,
                                            "author_is_blocked": false,
                                            "comment_type": null,
                                            "awarders": [],
                                            "mod_reason_by": null,
                                            "banned_by": null,
                                            "author_flair_type": "text",
                                            "total_awards_received": 0,
                                            "subreddit": "FredditFreebuild",
                                            "author_flair_template_id": null,
                                            "likes": null,
                                            "replies": "",
                                            "user_reports": [],
                                            "saved": false,
                                            "id": "cuijtu8",
                                            "banned_at_utc": null,
                                            "mod_reason_title": null,
                                            "gilded": 0,
                                            "archived": false,
                                            "collapsed_reason_code": null,
                                            "no_follow": true,
                                            "author": "NathanFazbear",
                                            "can_mod_post": false,
                                            "created_utc": 1440765808.0,
                                            "send_replies": true,
                                            "parent_id": "t1_cug2wbj",
                                            "score": 1,
                                            "author_fullname": "t2_jy86i",
                                            "removal_reason": null,
                                            "approved_by": null,
                                            "mod_note": null,
                                            "all_awardings": [],
                                            "body": "He comes on the server alot. He's OP I believe.",
                                            "edited": false,
                                            "top_awarded_type": null,
                                            "author_flair_css_class": null,
                                            "name": "t1_cuijtu8",
                                            "is_submitter": true,
                                            "downs": 0,
                                            "author_flair_richtext": [],
                                            "author_patreon_flair": false,
                                            "body_html": "&lt;div class=\"md\"&gt;&lt;p&gt;He comes on the server alot. He&amp;#39;s OP I believe.&lt;/p&gt;\n&lt;/div&gt;",
                                            "gildings": {},
                                            "collapsed_reason": null,
                                            "distinguished": null,
                                            "associated_award": null,
                                            "stickied": false,
                                            "author_premium": false,
                                            "can_gild": false,
                                            "link_id": "t3_3i7e24",
                                            "unrepliable_reason": null,
                                            "author_flair_text_color": "dark",
                                            "score_hidden": false,
                                            "permalink": "/r/FredditFreebuild/comments/3i7e24/a_word_to_everyone_who_hates_chris/cuijtu8/",
                                            "subreddit_type": "public",
                                            "locked": false,
                                            "report_reasons": null,
                                            "created": 1440765808.0,
                                            "author_flair_text": "Skool Sux",
                                            "treatment_tags": [],
                                            "collapsed": false,
                                            "subreddit_name_prefixed": "r/FredditFreebuild",
                                            "controversiality": 0,
                                            "depth": 1,
                                            "author_flair_background_color": "",
                                            "collapsed_because_crowd_control": null,
                                            "mod_reports": [],
                                            "num_reports": null,
                                            "ups": 1
                                        }
                                    }
                                ],
                                "before": null
                            }
                        },
                        "user_reports": [],
                        "saved": false,
                        "id": "cug2wbj",
                        "banned_at_utc": null,
                        "mod_reason_title": null,
                        "gilded": 0,
                        "archived": false,
                        "collapsed_reason_code": null,
                        "no_follow": true,
                        "author": "[deleted]",
                        "can_mod_post": false,
                        "send_replies": true,
                        "parent_id": "t3_3i7e24",
                        "score": 1,
                        "approved_by": null,
                        "report_reasons": null,
                        "all_awardings": [],
                        "subreddit_id": "t5_39dhr",
                        "body": "[deleted]",
                        "edited": false,
                        "downs": 0,
                        "author_flair_css_class": null,
                        "collapsed": false,
                        "is_submitter": false,
                        "body_html": "&lt;div class=\"md\"&gt;&lt;p&gt;[deleted]&lt;/p&gt;\n&lt;/div&gt;",
                        "gildings": {},
                        "collapsed_reason": null,
                        "associated_award": null,
                        "stickied": false,
                        "subreddit_type": "public",
                        "can_gild": false,
                        "top_awarded_type": null,
                        "unrepliable_reason": null,
                        "author_flair_text_color": "dark",
                        "score_hidden": false,
                        "permalink": "/r/FredditFreebuild/comments/3i7e24/a_word_to_everyone_who_hates_chris/cug2wbj/",
                        "num_reports": null,
                        "locked": false,
                        "name": "t1_cug2wbj",
                        "created": 1440580391.0,
                        "subreddit": "FredditFreebuild",
                        "author_flair_text": null,
                        "treatment_tags": [],
                        "created_utc": 1440580391.0,
                        "subreddit_name_prefixed": "r/FredditFreebuild",
                        "controversiality": 0,
                        "depth": 0,
                        "author_flair_background_color": "",
                        "collapsed_because_crowd_control": null,
                        "mod_reports": [],
                        "mod_note": null,
                        "distinguished": null
                    }
                },
                {
                    "kind": "t1",
                    "data": {
                        "subreddit_id": "t5_39dhr",
                        "approved_at_utc": null,
                        "author_is_blocked": false,
                        "comment_type": null,
                        "awarders": [],
                        "mod_reason_by": null,
                        "banned_by": null,
                        "author_flair_type": "text",
                        "total_awards_received": 0,
                        "subreddit": "FredditFreebuild",
                        "author_flair_template_id": null,
                        "likes": null,
                        "replies": "",
                        "user_reports": [],
                        "saved": false,
                        "id": "cudz5i4",
                        "banned_at_utc": null,
                        "mod_reason_title": null,
                        "gilded": 0,
                        "archived": false,
                        "collapsed_reason_code": null,
                        "no_follow": true,
                        "author": "Rockabyebaby",
                        "can_mod_post": false,
                        "created_utc": 1440430976.0,
                        "send_replies": true,
                        "parent_id": "t3_3i7e24",
                        "score": 1,
                        "author_fullname": "t2_c0hos",
                        "approved_by": null,
                        "mod_note": null,
                        "all_awardings": [],
                        "collapsed": false,
                        "body": "This. I never understood the pure hate towards Chris.",
                        "edited": false,
                        "top_awarded_type": null,
                        "author_flair_css_class": null,
                        "name": "t1_cudz5i4",
                        "is_submitter": false,
                        "downs": 0,
                        "author_flair_richtext": [],
                        "author_patreon_flair": false,
                        "body_html": "&lt;div class=\"md\"&gt;&lt;p&gt;This. I never understood the pure hate towards Chris.&lt;/p&gt;\n&lt;/div&gt;",
                        "removal_reason": null,
                        "collapsed_reason": null,
                        "distinguished": null,
                        "associated_award": null,
                        "stickied": false,
                        "author_premium": false,
                        "can_gild": false,
                        "gildings": {},
                        "unrepliable_reason": null,
                        "author_flair_text_color": null,
                        "score_hidden": false,
                        "permalink": "/r/FredditFreebuild/comments/3i7e24/a_word_to_everyone_who_hates_chris/cudz5i4/",
                        "subreddit_type": "public",
                        "locked": false,
                        "report_reasons": null,
                        "created": 1440430976.0,
                        "author_flair_text": null,
                        "treatment_tags": [],
                        "link_id": "t3_3i7e24",
                        "subreddit_name_prefixed": "r/FredditFreebuild",
                        "controversiality": 0,
                        "depth": 0,
                        "author_flair_background_color": null,
                        "collapsed_because_crowd_control": null,
                        "mod_reports": [],
                        "num_reports": null,
                        "ups": 1
                    }
                },
                {
                    "kind": "t1",
                    "data": {
                        "subreddit_id": "t5_39dhr",
                        "approved_at_utc": null,
                        "author_is_blocked": false,
                        "comment_type": null,
                        "awarders": [],
                        "mod_reason_by": null,
                        "banned_by": null,
                        "author_flair_type": "text",
                        "total_awards_received": 0,
                        "subreddit": "FredditFreebuild",
                        "author_flair_template_id": null,
                        "likes": null,
                        "replies": {
                            "kind": "Listing",
                            "data": {
                                "after": null,
                                "dist": null,
                                "modhash": "",
                                "geo_filter": "",
                                "children": [
                                    {
                                        "kind": "t1",
                                        "data": {
                                            "total_awards_received": 0,
                                            "approved_at_utc": null,
                                            "author_is_blocked": false,
                                            "comment_type": null,
                                            "awarders": [],
                                            "mod_reason_by": null,
                                            "banned_by": null,
                                            "ups": 3,
                                            "removal_reason": null,
                                            "link_id": "t3_3i7e24",
                                            "author_flair_template_id": null,
                                            "likes": null,
                                            "replies": "",
                                            "user_reports": [],
                                            "saved": false,
                                            "id": "cuear07",
                                            "banned_at_utc": null,
                                            "mod_reason_title": null,
                                            "gilded": 0,
                                            "archived": false,
                                            "collapsed_reason_code": null,
                                            "no_follow": true,
                                            "author": "[deleted]",
                                            "can_mod_post": false,
                                            "send_replies": true,
                                            "parent_id": "t1_cue06pw",
                                            "score": 3,
                                            "approved_by": null,
                                            "report_reasons": null,
                                            "all_awardings": [],
                                            "subreddit_id": "t5_39dhr",
                                            "body": "the hate has been growing for like a month now.",
                                            "edited": false,
                                            "author_flair_css_class": null,
                                            "collapsed": false,
                                            "downs": 0,
                                            "is_submitter": false,
                                            "body_html": "&lt;div class=\"md\"&gt;&lt;p&gt;the hate has been growing for like a month now.&lt;/p&gt;\n&lt;/div&gt;",
                                            "gildings": {},
                                            "collapsed_reason": null,
                                            "associated_award": null,
                                            "stickied": false,
                                            "subreddit_type": "public",
                                            "can_gild": false,
                                            "top_awarded_type": null,
                                            "unrepliable_reason": null,
                                            "author_flair_text_color": "dark",
                                            "score_hidden": false,
                                            "permalink": "/r/FredditFreebuild/comments/3i7e24/a_word_to_everyone_who_hates_chris/cuear07/",
                                            "num_reports": null,
                                            "locked": false,
                                            "name": "t1_cuear07",
                                            "created": 1440448719.0,
                                            "subreddit": "FredditFreebuild",
                                            "author_flair_text": null,
                                            "treatment_tags": [],
                                            "created_utc": 1440448719.0,
                                            "subreddit_name_prefixed": "r/FredditFreebuild",
                                            "controversiality": 0,
                                            "depth": 1,
                                            "author_flair_background_color": "",
                                            "collapsed_because_crowd_control": null,
                                            "mod_reports": [],
                                            "mod_note": null,
                                            "distinguished": null
                                        }
                                    }
                                ],
                                "before": null
                            }
                        },
                        "user_reports": [],
                        "saved": false,
                        "id": "cue06pw",
                        "banned_at_utc": null,
                        "mod_reason_title": null,
                        "gilded": 0,
                        "archived": false,
                        "collapsed_reason_code": null,
                        "no_follow": true,
                        "author": "Jaydn97",
                        "can_mod_post": false,
                        "created_utc": 1440432620.0,
                        "send_replies": true,
                        "parent_id": "t3_3i7e24",
                        "score": 0,
                        "author_fullname": "t2_l9h2n",
                        "approved_by": null,
                        "mod_note": null,
                        "all_awardings": [],
                        "collapsed": false,
                        "body": "I have anger issues too. i understand how i can be a dick like him sometimes and i can agree with most of this. but people don't like other people. hating won't stop because of people saying stop. just let the hate grow and they will get bored",
                        "edited": false,
                        "top_awarded_type": null,
                        "author_flair_css_class": null,
                        "name": "t1_cue06pw",
                        "is_submitter": false,
                        "downs": 0,
                        "author_flair_richtext": [],
                        "author_patreon_flair": false,
                        "body_html": "&lt;div class=\"md\"&gt;&lt;p&gt;I have anger issues too. i understand how i can be a dick like him sometimes and i can agree with most of this. but people don&amp;#39;t like other people. hating won&amp;#39;t stop because of people saying stop. just let the hate grow and they will get bored&lt;/p&gt;\n&lt;/div&gt;",
                        "removal_reason": null,
                        "collapsed_reason": null,
                        "distinguished": null,
                        "associated_award": null,
                        "stickied": false,
                        "author_premium": false,
                        "can_gild": false,
                        "gildings": {},
                        "unrepliable_reason": null,
                        "author_flair_text_color": null,
                        "score_hidden": false,
                        "permalink": "/r/FredditFreebuild/comments/3i7e24/a_word_to_everyone_who_hates_chris/cue06pw/",
                        "subreddit_type": "public",
                        "locked": false,
                        "report_reasons": null,
                        "created": 1440432620.0,
                        "author_flair_text": null,
                        "treatment_tags": [],
                        "link_id": "t3_3i7e24",
                        "subreddit_name_prefixed": "r/FredditFreebuild",
                        "controversiality": 0,
                        "depth": 0,
                        "author_flair_background_color": null,
                        "collapsed_because_crowd_control": null,
                        "mod_reports": [],
                        "num_reports": null,
                        "ups": 0
                    }
                }
            ],
            "before": null
        }
    }
]