[
    {
        "kind": "Listing",
        "data": {
            "after": null,
            "dist": 1,
            "modhash": "",
            "geo_filter": "",
            "children": [
                {
                    "kind": "t3",
                    "data": {
                        "approved_at_utc": null,
                        "subreddit": "Freebuild",
                        "selftext": "",
                        "user_reports": [],
                        "saved": false,
                        "mod_reason_title": null,
                        "gilded": 0,
                        "clicked": false,
                        "title": "YoU",
                        "link_flair_richtext": [],
                        "subreddit_name_prefixed": "r/Freebuild",
                        "hidden": false,
                        "pwls": null,
                        "link_flair_css_class": null,
                        "downs": 0,
                        "thumbnail_height": 72,
                        "top_awarded_type": null,
                        "parent_whitelist_status": null,
                        "hide_score": false,
                        "name": "t3_54sa8j",
                        "quarantine": false,
                        "link_flair_text_color": "dark",
                        "upvote_ratio": 1.0,
                        "author_flair_background_color": "",
                        "subreddit_type": "public",
                        "ups": 3,
                        "total_awards_received": 0,
                        "media_embed": {},
                        "thumbnail_width": 140,
                        "author_flair_template_id": null,
                        "is_original_content": false,
                        "secure_media": null,
                        "is_reddit_media_domain": false,
                        "is_meta": false,
                        "category": null,
                        "secure_media_embed": {},
                        "link_flair_text": null,
                        "can_mod_post": false,
                        "score": 3,
                        "approved_by": null,
                        "is_created_from_ads_ui": false,
                        "thumbnail": "https://b.thumbs.redditmedia.com/OckFJ6F7682HwrbbQ886v1_T42E79mpUDOztzy0nYDA.jpg",
                        "edited": false,
                        "author_flair_css_class": null,
                        "gildings": {},
                        "post_hint": "link",
                        "content_categories": null,
                        "is_self": false,
                        "mod_note": null,
                        "created": 1475003940.0,
                        "link_flair_type": "text",
                        "wls": null,
                        "removed_by_category": null,
                        "banned_by": null,
                        "domain": "imgur.com",
                        "allow_live_comments": false,
                        "selftext_html": null,
                        "likes": null,
                        "suggested_sort": null,
                        "banned_at_utc": null,
                        "url_overridden_by_dest": "http://imgur.com/a/ICub6",
                        "view_count": null,
                        "archived": false,
                        "no_follow": true,
                        "is_crosspostable": false,
                        "pinned": false,
                        "over_18": false,
                        "preview": {
                            "images": [
                                {
                                    "source": {
                                        "url": "https://external-preview.redd.it/4P9ZZSBwVTiYjw5B5j4BgUOAZKkGn6rKNgs5QGH4Ip8.jpg?auto=webp&amp;s=962443c724c4fa51341b56326665ed2924e6f066",
                                        "width": 1366,
                                        "height": 705
                                    },
                                    "resolutions": [
                                        {
                                            "url": "https://external-preview.redd.it/4P9ZZSBwVTiYjw5B5j4BgUOAZKkGn6rKNgs5QGH4Ip8.jpg?width=108&amp;crop=smart&amp;auto=webp&amp;s=4b36606177ffed8c8d50ce6960198cbaf40b204a",
                                            "width": 108,
                                            "height": 55
                                        },
                                        {
                                            "url": "https://external-preview.redd.it/4P9ZZSBwVTiYjw5B5j4BgUOAZKkGn6rKNgs5QGH4Ip8.jpg?width=216&amp;crop=smart&amp;auto=webp&amp;s=6d507b5517275acca4606ca9183554ae66959333",
                                            "width": 216,
                                            "height": 111
                                        },
                                        {
                                            "url": "https://external-preview.redd.it/4P9ZZSBwVTiYjw5B5j4BgUOAZKkGn6rKNgs5QGH4Ip8.jpg?width=320&amp;crop=smart&amp;auto=webp&amp;s=33b574b809ff7662b8d27de5795f9979d8b5f7c2",
                                            "width": 320,
                                            "height": 165
                                        },
                                        {
                                            "url": "https://external-preview.redd.it/4P9ZZSBwVTiYjw5B5j4BgUOAZKkGn6rKNgs5QGH4Ip8.jpg?width=640&amp;crop=smart&amp;auto=webp&amp;s=5f75ed5f2b5de219f5f4adad7712e55e75111d0f",
                                            "width": 640,
                                            "height": 330
                                        },
                                        {
                                            "url": "https://external-preview.redd.it/4P9ZZSBwVTiYjw5B5j4BgUOAZKkGn6rKNgs5QGH4Ip8.jpg?width=960&amp;crop=smart&amp;auto=webp&amp;s=38456bd5008b784a24c00406e3cd9dfafb72ca2d",
                                            "width": 960,
                                            "height": 495
                                        },
                                        {
                                            "url": "https://external-preview.redd.it/4P9ZZSBwVTiYjw5B5j4BgUOAZKkGn6rKNgs5QGH4Ip8.jpg?width=1080&amp;crop=smart&amp;auto=webp&amp;s=bdc28c838e683b82216494f9b62b492be82b41b4",
                                            "width": 1080,
                                            "height": 557
                                        }
                                    ],
                                    "variants": {},
                                    "id": "fFHsueLzoUVN9jDVMRHyd1J3I4iajO4bRFHb9iJsxc0"
                                }
                            ],
                            "enabled": false
                        },
                        "all_awardings": [],
                        "awarders": [],
                        "media_only": false,
                        "can_gild": false,
                        "spoiler": false,
                        "locked": false,
                        "author_flair_text": null,
                        "treatment_tags": [],
                        "visited": false,
                        "removed_by": null,
                        "num_reports": null,
                        "distinguished": null,
                        "subreddit_id": "t5_3bg30",
                        "author_is_blocked": false,
                        "mod_reason_by": null,
                        "removal_reason": null,
                        "link_flair_background_color": "",
                        "id": "54sa8j",
                        "is_robot_indexable": true,
                        "num_duplicates": 0,
                        "report_reasons": null,
                        "author": "[deleted]",
                        "discussion_type": null,
                        "num_comments": 3,
                        "send_replies": true,
                        "media": null,
                        "contest_mode": false,
                        "author_flair_text_color": "dark",
                        "permalink": "/r/Freebuild/comments/54sa8j/you/",
                        "whitelist_status": null,
                        "stickied": false,
                        "url": "http://imgur.com/a/ICub6",
                        "subreddit_subscribers": 219,
                        "created_utc": 1475003940.0,
                        "num_crossposts": 0,
                        "mod_reports": [],
                        "is_video": false
                    }
                }
            ],
            "before": null
        }
    },
    {
        "kind": "Listing",
        "data": {
            "after": null,
            "dist": null,
            "modhash": "",
            "geo_filter": "",
            "children": [
                {
                    "kind": "t1",
                    "data": {
                        "total_awards_received": 0,
                        "approved_at_utc": null,
                        "author_is_blocked": false,
                        "comment_type": null,
                        "awarders": [],
                        "mod_reason_by": null,
                        "banned_by": null,
                        "ups": 1,
                        "removal_reason": null,
                        "link_id": "t3_54sa8j",
                        "author_flair_template_id": null,
                        "likes": null,
                        "replies": {
                            "kind": "Listing",
                            "data": {
                                "after": null,
                                "dist": null,
                                "modhash": "",
                                "geo_filter": "",
                                "children": [
                                    {
                                        "kind": "t1",
                                        "data": {
                                            "total_awards_received": 0,
                                            "approved_at_utc": null,
                                            "author_is_blocked": false,
                                            "comment_type": null,
                                            "awarders": [],
                                            "mod_reason_by": null,
                                            "banned_by": null,
                                            "ups": 1,
                                            "removal_reason": null,
                                            "link_id": "t3_54sa8j",
                                            "author_flair_template_id": null,
                                            "likes": null,
                                            "replies": "",
                                            "user_reports": [],
                                            "saved": false,
                                            "id": "d84hx48",
                                            "banned_at_utc": null,
                                            "mod_reason_title": null,
                                            "gilded": 0,
                                            "archived": false,
                                            "collapsed_reason_code": null,
                                            "no_follow": true,
                                            "author": "[deleted]",
                                            "can_mod_post": false,
                                            "send_replies": true,
                                            "parent_id": "t1_d84hvql",
                                            "score": 1,
                                            "approved_by": null,
                                            "report_reasons": null,
                                            "all_awardings": [],
                                            "subreddit_id": "t5_3bg30",
                                            "body": "hey it's YoU.",
                                            "edited": false,
                                            "author_flair_css_class": null,
                                            "collapsed": false,
                                            "downs": 0,
                                            "is_submitter": false,
                                            "body_html": "&lt;div class=\"md\"&gt;&lt;p&gt;hey it&amp;#39;s YoU.&lt;/p&gt;\n&lt;/div&gt;",
                                            "gildings": {},
                                            "collapsed_reason": null,
                                            "associated_award": null,
                                            "stickied": false,
                                            "subreddit_type": "public",
                                            "can_gild": false,
                                            "top_awarded_type": null,
                                            "unrepliable_reason": null,
                                            "author_flair_text_color": "dark",
                                            "score_hidden": false,
                                            "permalink": "/r/Freebuild/comments/54sa8j/you/d84hx48/",
                                            "num_reports": null,
                                            "locked": false,
                                            "name": "t1_d84hx48",
                                            "created": 1475004034.0,
                                            "subreddit": "Freebuild",
                                            "author_flair_text": null,
                                            "treatment_tags": [],
                                            "created_utc": 1475004034.0,
                                            "subreddit_name_prefixed": "r/Freebuild",
                                            "controversiality": 0,
                                            "depth": 1,
                                            "author_flair_background_color": "",
                                            "collapsed_because_crowd_control": null,
                                            "mod_reports": [],
                                            "mod_note": null,
                                            "distinguished": null
                                        }
                                    }
                                ],
                                "before": null
                            }
                        },
                        "user_reports": [],
                        "saved": false,
                        "id": "d84hvql",
                        "banned_at_utc": null,
                        "mod_reason_title": null,
                        "gilded": 0,
                        "archived": false,
                        "collapsed_reason_code": null,
                        "no_follow": true,
                        "author": "[deleted]",
                        "can_mod_post": false,
                        "send_replies": true,
                        "parent_id": "t3_54sa8j",
                        "score": 1,
                        "approved_by": null,
                        "report_reasons": null,
                        "all_awardings": [],
                        "subreddit_id": "t5_3bg30",
                        "body": "[deleted]",
                        "edited": false,
                        "downs": 0,
                        "author_flair_css_class": null,
                        "collapsed": false,
                        "is_submitter": false,
                        "body_html": "&lt;div class=\"md\"&gt;&lt;p&gt;[deleted]&lt;/p&gt;\n&lt;/div&gt;",
                        "gildings": {},
                        "collapsed_reason": null,
                        "associated_award": null,
                        "stickied": false,
                        "subreddit_type": "public",
                        "can_gild": false,
                        "top_awarded_type": null,
                        "unrepliable_reason": null,
                        "author_flair_text_color": "dark",
                        "score_hidden": false,
                        "permalink": "/r/Freebuild/comments/54sa8j/you/d84hvql/",
                        "num_reports": null,
                        "locked": false,
                        "name": "t1_d84hvql",
                        "created": 1475003985.0,
                        "subreddit": "Freebuild",
                        "author_flair_text": null,
                        "treatment_tags": [],
                        "created_utc": 1475003985.0,
                        "subreddit_name_prefixed": "r/Freebuild",
                        "controversiality": 0,
                        "depth": 0,
                        "author_flair_background_color": "",
                        "collapsed_because_crowd_control": null,
                        "mod_reports": [],
                        "mod_note": null,
                        "distinguished": null
                    }
                },
                {
                    "kind": "t1",
                    "data": {
                        "subreddit_id": "t5_3bg30",
                        "approved_at_utc": null,
                        "author_is_blocked": false,
                        "comment_type": null,
                        "awarders": [],
                        "mod_reason_by": null,
                        "banned_by": null,
                        "author_flair_type": "text",
                        "total_awards_received": 0,
                        "subreddit": "Freebuild",
                        "author_flair_template_id": null,
                        "likes": null,
                        "replies": "",
                        "user_reports": [],
                        "saved": false,
                        "id": "d84p8i8",
                        "banned_at_utc": null,
                        "mod_reason_title": null,
                        "gilded": 0,
                        "archived": false,
                        "collapsed_reason_code": null,
                        "no_follow": true,
                        "author": "PigLadAl",
                        "can_mod_post": false,
                        "created_utc": 1475013521.0,
                        "send_replies": true,
                        "parent_id": "t3_54sa8j",
                        "score": 1,
                        "author_fullname": "t2_erfid",
                        "approved_by": null,
                        "mod_note": null,
                        "all_awardings": [],
                        "collapsed": false,
                        "body": "2spooky4me",
                        "edited": false,
                        "top_awarded_type": null,
                        "author_flair_css_class": "",
                        "name": "t1_d84p8i8",
                        "is_submitter": false,
                        "downs": 0,
                        "author_flair_richtext": [],
                        "author_patreon_flair": false,
                        "body_html": "&lt;div class=\"md\"&gt;&lt;p&gt;2spooky4me&lt;/p&gt;\n&lt;/div&gt;",
                        "removal_reason": null,
                        "collapsed_reason": null,
                        "distinguished": null,
                        "associated_award": null,
                        "stickied": false,
                        "author_premium": false,
                        "can_gild": false,
                        "gildings": {},
                        "unrepliable_reason": null,
                        "author_flair_text_color": "dark",
                        "score_hidden": false,
                        "permalink": "/r/Freebuild/comments/54sa8j/you/d84p8i8/",
                        "subreddit_type": "public",
                        "locked": false,
                        "report_reasons": null,
                        "created": 1475013521.0,
                        "author_flair_text": "Beaned",
                        "treatment_tags": [],
                        "link_id": "t3_54sa8j",
                        "subreddit_name_prefixed": "r/Freebuild",
                        "controversiality": 0,
                        "depth": 0,
                        "author_flair_background_color": "",
                        "collapsed_because_crowd_control": null,
                        "mod_reports": [],
                        "num_reports": null,
                        "ups": 1
                    }
                },
                {
                    "kind": "t1",
                    "data": {
                        "subreddit_id": "t5_3bg30",
                        "approved_at_utc": null,
                        "author_is_blocked": false,
                        "comment_type": null,
                        "awarders": [],
                        "mod_reason_by": null,
                        "banned_by": null,
                        "author_flair_type": "text",
                        "total_awards_received": 0,
                        "subreddit": "Freebuild",
                        "author_flair_template_id": null,
                        "likes": null,
                        "replies": "",
                        "user_reports": [],
                        "saved": false,
                        "id": "d86l2tn",
                        "banned_at_utc": null,
                        "mod_reason_title": null,
                        "gilded": 0,
                        "archived": false,
                        "collapsed_reason_code": null,
                        "no_follow": true,
                        "author": "Satisfyer",
                        "can_mod_post": false,
                        "created_utc": 1475128248.0,
                        "send_replies": true,
                        "parent_id": "t3_54sa8j",
                        "score": 1,
                        "author_fullname": "t2_o24p9",
                        "approved_by": null,
                        "mod_note": null,
                        "all_awardings": [],
                        "collapsed": false,
                        "body": "he",
                        "edited": false,
                        "top_awarded_type": null,
                        "author_flair_css_class": "",
                        "name": "t1_d86l2tn",
                        "is_submitter": false,
                        "downs": 0,
                        "author_flair_richtext": [],
                        "author_patreon_flair": false,
                        "body_html": "&lt;div class=\"md\"&gt;&lt;p&gt;he&lt;/p&gt;\n&lt;/div&gt;",
                        "removal_reason": null,
                        "collapsed_reason": null,
                        "distinguished": null,
                        "associated_award": null,
                        "stickied": false,
                        "author_premium": false,
                        "can_gild": false,
                        "gildings": {},
                        "unrepliable_reason": null,
                        "author_flair_text_color": "dark",
                        "score_hidden": false,
                        "permalink": "/r/Freebuild/comments/54sa8j/you/d86l2tn/",
                        "subreddit_type": "public",
                        "locked": false,
                        "report_reasons": null,
                        "created": 1475128248.0,
                        "author_flair_text": "SPEICL BOI",
                        "treatment_tags": [],
                        "link_id": "t3_54sa8j",
                        "subreddit_name_prefixed": "r/Freebuild",
                        "controversiality": 0,
                        "depth": 0,
                        "author_flair_background_color": "",
                        "collapsed_because_crowd_control": null,
                        "mod_reports": [],
                        "num_reports": null,
                        "ups": 1
                    }
                }
            ],
            "before": null
        }
    }
]