[
    {
        "kind": "Listing",
        "data": {
            "after": null,
            "dist": 1,
            "modhash": "",
            "geo_filter": "",
            "children": [
                {
                    "kind": "t3",
                    "data": {
                        "approved_at_utc": null,
                        "subreddit": "Freebuild",
                        "selftext": "#Chronology of events\n\nHighlighted the most important parts\n\n- A random dude named \"kekkekkekkekkekkekkk\" posts [this](http://imgur.com/a/dNSUL)\n\n- That kekguy also comments on posts with insults\n\n- Comments \"foreshadowing\" on TFOF Season 3 Recap\n\n- Gets banned, and is incredibly disrespectful [here](http://imgur.com/a/8fSKI)\n\n- Staff launches \"investigation\" on who this guy is.\n\n- Sends [this](http://imgur.com/a/x2odT) to Jeff\n\n- **Jeff has had some drug complications in the past, he has recovered but kekguy sends him [this](http://imgur.com/a/E2zjT), which shows us that he had inside knowledge of Freddit.**\n\n- DEFCON 4\n\n- Says [this](http://imgur.com/a/SM0A3) which corresponded to DarkArtswork - we're not sure if he was intentionally pinning the blame on him or if he wrote a random number\n\n- [Fake news](http://imgur.com/a/ZufSO) it's actually just kekguy alone\n\n- **Starts threatening the server and starts uncovering shit from people's past - including Sven's**\n\n- Staff is dedicating all it's time to investigate who it is, and narrows it down to 4 or 5 suspects.\n\n- Server is backed up\n\n- Says some more cryptic edgy bullshit - \"The end is soon, all secrets will be revealed\"\n\n- His threats and crypticness pushes Zelda into feeling uneasy (a guy already framed Zelda for something, and followed him around, so he thought it was that guy) and Soda into feeling [panicked](http://imgur.com/a/CXVeF), to the point he leaves the discord.\n\n- **Joins the minecraft server through an alt**\n\n- **Starts to maintain contact with Zelda** some [transcripts](http://imgur.com/a/LCZya) where he admits he's trying to stirr up drama, trying to see the \"reaction\" of groups, and that he has some \"group\" that tests various discord servers - its all bullshit\n\n- Staff starts planning how to find out who he is, I set up a bait \n\n- The first bait fails, I throw in a second one. \n\n- [Little does he know it's gonna end in some minutes.](http://imgur.com/a/W9jIw)\n\n- **He bites the bait**\n\n- I compare data, matches up with a Freddittor. I set up a discord server to confirm my suspicions.\n\n- #[He confirms the data - kekguy is pres](http://imgur.com/a/3rICH)\n\n- [Full log of the alt confirming he's pres](https://cdn.discordapp.com/attachments/310916574733271040/316676788040368128/kekguyispres.txt)\n\n- Pres is permanent banned, IP permanent banned, banned from the discord for breaking a bunch of rules in a very big way.\n\n- DEFCON 5 - All server functionalities are back to normal.\n\nSo yeah, pres is the guy who harassed Jeff, caused panic and drama, lied, etc etc i just listed what happened above this is pretty much redundant.\n\nSecond time he pulls a lying scheme on us. Welp, I guess some people don't learn.\n\n---\n\nI just want to congratulate the Staff for keeping their heads cool during the proccess, and not leaking anything outside of #staff, so much so that nobody knew that was going on for two days. No drama happened besides the minor confusion about the kekguy.\n\nIt was dealt accordingly and in excellent team work. I hope this cleared things out on what happened, and the name of the event officially is **The Impresonating of 2k17**.\n\nKeep discussion civil. That's all for now, thanks for reading and catching up!\n\n- Zoo Man",
                        "user_reports": [],
                        "saved": false,
                        "mod_reason_title": null,
                        "gilded": 0,
                        "clicked": false,
                        "title": "CRISIS ADVERTED - kekkekkekkekk Identity Revealed",
                        "link_flair_richtext": [],
                        "subreddit_name_prefixed": "r/Freebuild",
                        "hidden": false,
                        "pwls": null,
                        "link_flair_css_class": "",
                        "downs": 0,
                        "thumbnail_height": null,
                        "top_awarded_type": null,
                        "parent_whitelist_status": null,
                        "hide_score": false,
                        "name": "t3_6cxg3k",
                        "quarantine": false,
                        "link_flair_text_color": null,
                        "upvote_ratio": 0.91,
                        "author_flair_background_color": "",
                        "subreddit_type": "public",
                        "ups": 8,
                        "total_awards_received": 0,
                        "media_embed": {},
                        "thumbnail_width": null,
                        "author_flair_template_id": null,
                        "is_original_content": false,
                        "author_fullname": "t2_hsaxm",
                        "secure_media": null,
                        "is_reddit_media_domain": false,
                        "is_meta": false,
                        "category": null,
                        "secure_media_embed": {},
                        "link_flair_text": "PRES IS BANNED",
                        "can_mod_post": false,
                        "score": 8,
                        "approved_by": null,
                        "is_created_from_ads_ui": false,
                        "author_premium": false,
                        "thumbnail": "self",
                        "edited": 1513824342.0,
                        "author_flair_css_class": null,
                        "author_flair_richtext": [],
                        "gildings": {},
                        "post_hint": "self",
                        "content_categories": null,
                        "is_self": true,
                        "mod_note": null,
                        "created": 1495572556.0,
                        "link_flair_type": "text",
                        "wls": null,
                        "removed_by_category": null,
                        "banned_by": null,
                        "author_flair_type": "text",
                        "domain": "self.Freebuild",
                        "allow_live_comments": false,
                        "selftext_html": "&lt;!-- SC_OFF --&gt;&lt;div class=\"md\"&gt;&lt;h1&gt;Chronology of events&lt;/h1&gt;\n\n&lt;p&gt;Highlighted the most important parts&lt;/p&gt;\n\n&lt;ul&gt;\n&lt;li&gt;&lt;p&gt;A random dude named &amp;quot;kekkekkekkekkekkekkk&amp;quot; posts &lt;a href=\"http://imgur.com/a/dNSUL\"&gt;this&lt;/a&gt;&lt;/p&gt;&lt;/li&gt;\n&lt;li&gt;&lt;p&gt;That kekguy also comments on posts with insults&lt;/p&gt;&lt;/li&gt;\n&lt;li&gt;&lt;p&gt;Comments &amp;quot;foreshadowing&amp;quot; on TFOF Season 3 Recap&lt;/p&gt;&lt;/li&gt;\n&lt;li&gt;&lt;p&gt;Gets banned, and is incredibly disrespectful &lt;a href=\"http://imgur.com/a/8fSKI\"&gt;here&lt;/a&gt;&lt;/p&gt;&lt;/li&gt;\n&lt;li&gt;&lt;p&gt;Staff launches &amp;quot;investigation&amp;quot; on who this guy is.&lt;/p&gt;&lt;/li&gt;\n&lt;li&gt;&lt;p&gt;Sends &lt;a href=\"http://imgur.com/a/x2odT\"&gt;this&lt;/a&gt; to Jeff&lt;/p&gt;&lt;/li&gt;\n&lt;li&gt;&lt;p&gt;&lt;strong&gt;Jeff has had some drug complications in the past, he has recovered but kekguy sends him &lt;a href=\"http://imgur.com/a/E2zjT\"&gt;this&lt;/a&gt;, which shows us that he had inside knowledge of Freddit.&lt;/strong&gt;&lt;/p&gt;&lt;/li&gt;\n&lt;li&gt;&lt;p&gt;DEFCON 4&lt;/p&gt;&lt;/li&gt;\n&lt;li&gt;&lt;p&gt;Says &lt;a href=\"http://imgur.com/a/SM0A3\"&gt;this&lt;/a&gt; which corresponded to DarkArtswork - we&amp;#39;re not sure if he was intentionally pinning the blame on him or if he wrote a random number&lt;/p&gt;&lt;/li&gt;\n&lt;li&gt;&lt;p&gt;&lt;a href=\"http://imgur.com/a/ZufSO\"&gt;Fake news&lt;/a&gt; it&amp;#39;s actually just kekguy alone&lt;/p&gt;&lt;/li&gt;\n&lt;li&gt;&lt;p&gt;&lt;strong&gt;Starts threatening the server and starts uncovering shit from people&amp;#39;s past - including Sven&amp;#39;s&lt;/strong&gt;&lt;/p&gt;&lt;/li&gt;\n&lt;li&gt;&lt;p&gt;Staff is dedicating all it&amp;#39;s time to investigate who it is, and narrows it down to 4 or 5 suspects.&lt;/p&gt;&lt;/li&gt;\n&lt;li&gt;&lt;p&gt;Server is backed up&lt;/p&gt;&lt;/li&gt;\n&lt;li&gt;&lt;p&gt;Says some more cryptic edgy bullshit - &amp;quot;The end is soon, all secrets will be revealed&amp;quot;&lt;/p&gt;&lt;/li&gt;\n&lt;li&gt;&lt;p&gt;His threats and crypticness pushes Zelda into feeling uneasy (a guy already framed Zelda for something, and followed him around, so he thought it was that guy) and Soda into feeling &lt;a href=\"http://imgur.com/a/CXVeF\"&gt;panicked&lt;/a&gt;, to the point he leaves the discord.&lt;/p&gt;&lt;/li&gt;\n&lt;li&gt;&lt;p&gt;&lt;strong&gt;Joins the minecraft server through an alt&lt;/strong&gt;&lt;/p&gt;&lt;/li&gt;\n&lt;li&gt;&lt;p&gt;&lt;strong&gt;Starts to maintain contact with Zelda&lt;/strong&gt; some &lt;a href=\"http://imgur.com/a/LCZya\"&gt;transcripts&lt;/a&gt; where he admits he&amp;#39;s trying to stirr up drama, trying to see the &amp;quot;reaction&amp;quot; of groups, and that he has some &amp;quot;group&amp;quot; that tests various discord servers - its all bullshit&lt;/p&gt;&lt;/li&gt;\n&lt;li&gt;&lt;p&gt;Staff starts planning how to find out who he is, I set up a bait &lt;/p&gt;&lt;/li&gt;\n&lt;li&gt;&lt;p&gt;The first bait fails, I throw in a second one. &lt;/p&gt;&lt;/li&gt;\n&lt;li&gt;&lt;p&gt;&lt;a href=\"http://imgur.com/a/W9jIw\"&gt;Little does he know it&amp;#39;s gonna end in some minutes.&lt;/a&gt;&lt;/p&gt;&lt;/li&gt;\n&lt;li&gt;&lt;p&gt;&lt;strong&gt;He bites the bait&lt;/strong&gt;&lt;/p&gt;&lt;/li&gt;\n&lt;li&gt;&lt;p&gt;I compare data, matches up with a Freddittor. I set up a discord server to confirm my suspicions.&lt;/p&gt;&lt;/li&gt;\n&lt;li&gt;&lt;h1&gt;&lt;a href=\"http://imgur.com/a/3rICH\"&gt;He confirms the data - kekguy is pres&lt;/a&gt;&lt;/h1&gt;&lt;/li&gt;\n&lt;li&gt;&lt;p&gt;&lt;a href=\"https://cdn.discordapp.com/attachments/310916574733271040/316676788040368128/kekguyispres.txt\"&gt;Full log of the alt confirming he&amp;#39;s pres&lt;/a&gt;&lt;/p&gt;&lt;/li&gt;\n&lt;li&gt;&lt;p&gt;Pres is permanent banned, IP permanent banned, banned from the discord for breaking a bunch of rules in a very big way.&lt;/p&gt;&lt;/li&gt;\n&lt;li&gt;&lt;p&gt;DEFCON 5 - All server functionalities are back to normal.&lt;/p&gt;&lt;/li&gt;\n&lt;/ul&gt;\n\n&lt;p&gt;So yeah, pres is the guy who harassed Jeff, caused panic and drama, lied, etc etc i just listed what happened above this is pretty much redundant.&lt;/p&gt;\n\n&lt;p&gt;Second time he pulls a lying scheme on us. Welp, I guess some people don&amp;#39;t learn.&lt;/p&gt;\n\n&lt;hr/&gt;\n\n&lt;p&gt;I just want to congratulate the Staff for keeping their heads cool during the proccess, and not leaking anything outside of #staff, so much so that nobody knew that was going on for two days. No drama happened besides the minor confusion about the kekguy.&lt;/p&gt;\n\n&lt;p&gt;It was dealt accordingly and in excellent team work. I hope this cleared things out on what happened, and the name of the event officially is &lt;strong&gt;The Impresonating of 2k17&lt;/strong&gt;.&lt;/p&gt;\n\n&lt;p&gt;Keep discussion civil. That&amp;#39;s all for now, thanks for reading and catching up!&lt;/p&gt;\n\n&lt;ul&gt;\n&lt;li&gt;Zoo Man&lt;/li&gt;\n&lt;/ul&gt;\n&lt;/div&gt;&lt;!-- SC_ON --&gt;",
                        "likes": null,
                        "suggested_sort": null,
                        "banned_at_utc": null,
                        "view_count": null,
                        "archived": false,
                        "no_follow": false,
                        "is_crosspostable": false,
                        "pinned": false,
                        "over_18": false,
                        "preview": {
                            "images": [
                                {
                                    "source": {
                                        "url": "https://external-preview.redd.it/nvNZsDta2v7WAEBxMXja4JUX8WbrCBKUHW3qYFzG89k.jpg?auto=webp&amp;s=f809f00c52b02f04250e4e588a16372bb7c0c6d0",
                                        "width": 382,
                                        "height": 131
                                    },
                                    "resolutions": [
                                        {
                                            "url": "https://external-preview.redd.it/nvNZsDta2v7WAEBxMXja4JUX8WbrCBKUHW3qYFzG89k.jpg?width=108&amp;crop=smart&amp;auto=webp&amp;s=d282ff963e62cffa43179526bf94aec3f678b2ae",
                                            "width": 108,
                                            "height": 37
                                        },
                                        {
                                            "url": "https://external-preview.redd.it/nvNZsDta2v7WAEBxMXja4JUX8WbrCBKUHW3qYFzG89k.jpg?width=216&amp;crop=smart&amp;auto=webp&amp;s=3f5cfbecd48651c81619b72342569a274d21738d",
                                            "width": 216,
                                            "height": 74
                                        },
                                        {
                                            "url": "https://external-preview.redd.it/nvNZsDta2v7WAEBxMXja4JUX8WbrCBKUHW3qYFzG89k.jpg?width=320&amp;crop=smart&amp;auto=webp&amp;s=5cd35886cbfe4969d4718ad8fe2cb4267bc85c7a",
                                            "width": 320,
                                            "height": 109
                                        }
                                    ],
                                    "variants": {},
                                    "id": "EbVGbptvq-DbZ5I_zrCDO660gumvOH6XfraEmKNlmow"
                                }
                            ],
                            "enabled": false
                        },
                        "all_awardings": [],
                        "awarders": [],
                        "media_only": false,
                        "can_gild": false,
                        "spoiler": false,
                        "locked": false,
                        "author_flair_text": "T.B.C",
                        "treatment_tags": [],
                        "visited": false,
                        "removed_by": null,
                        "num_reports": null,
                        "distinguished": null,
                        "subreddit_id": "t5_3bg30",
                        "author_is_blocked": false,
                        "mod_reason_by": null,
                        "removal_reason": null,
                        "link_flair_background_color": null,
                        "id": "6cxg3k",
                        "is_robot_indexable": true,
                        "num_duplicates": 0,
                        "report_reasons": null,
                        "author": "Zoocanadanda",
                        "discussion_type": null,
                        "num_comments": 8,
                        "send_replies": true,
                        "media": null,
                        "contest_mode": false,
                        "author_patreon_flair": false,
                        "author_flair_text_color": "dark",
                        "permalink": "/r/Freebuild/comments/6cxg3k/crisis_adverted_kekkekkekkekk_identity_revealed/",
                        "whitelist_status": null,
                        "stickied": false,
                        "url": "https://old.reddit.com/r/Freebuild/comments/6cxg3k/crisis_adverted_kekkekkekkekk_identity_revealed/",
                        "subreddit_subscribers": 219,
                        "created_utc": 1495572556.0,
                        "num_crossposts": 0,
                        "mod_reports": [],
                        "is_video": false
                    }
                }
            ],
            "before": null
        }
    },
    {
        "kind": "Listing",
        "data": {
            "after": null,
            "dist": null,
            "modhash": "",
            "geo_filter": "",
            "children": [
                {
                    "kind": "t1",
                    "data": {
                        "subreddit_id": "t5_3bg30",
                        "approved_at_utc": null,
                        "author_is_blocked": false,
                        "comment_type": null,
                        "awarders": [],
                        "mod_reason_by": null,
                        "banned_by": null,
                        "author_flair_type": "text",
                        "total_awards_received": 0,
                        "subreddit": "Freebuild",
                        "author_flair_template_id": null,
                        "likes": null,
                        "replies": "",
                        "user_reports": [],
                        "saved": false,
                        "id": "dhy67fv",
                        "banned_at_utc": null,
                        "mod_reason_title": null,
                        "gilded": 0,
                        "archived": false,
                        "collapsed_reason_code": null,
                        "no_follow": false,
                        "author": "--jeffp--",
                        "can_mod_post": false,
                        "created_utc": 1495575183.0,
                        "send_replies": true,
                        "parent_id": "t3_6cxg3k",
                        "score": 3,
                        "author_fullname": "t2_8a2hti",
                        "approved_by": null,
                        "mod_note": null,
                        "all_awardings": [],
                        "collapsed": false,
                        "body": "Wow. Just... wow. That's all I can say about this. ",
                        "edited": false,
                        "top_awarded_type": null,
                        "author_flair_css_class": "",
                        "name": "t1_dhy67fv",
                        "is_submitter": false,
                        "downs": 0,
                        "author_flair_richtext": [],
                        "author_patreon_flair": false,
                        "body_html": "&lt;div class=\"md\"&gt;&lt;p&gt;Wow. Just... wow. That&amp;#39;s all I can say about this. &lt;/p&gt;\n&lt;/div&gt;",
                        "removal_reason": null,
                        "collapsed_reason": null,
                        "distinguished": null,
                        "associated_award": null,
                        "stickied": false,
                        "author_premium": false,
                        "can_gild": false,
                        "gildings": {},
                        "unrepliable_reason": null,
                        "author_flair_text_color": "dark",
                        "score_hidden": false,
                        "permalink": "/r/Freebuild/comments/6cxg3k/crisis_adverted_kekkekkekkekk_identity_revealed/dhy67fv/",
                        "subreddit_type": "public",
                        "locked": false,
                        "report_reasons": null,
                        "created": 1495575183.0,
                        "author_flair_text": "DEAD",
                        "treatment_tags": [],
                        "link_id": "t3_6cxg3k",
                        "subreddit_name_prefixed": "r/Freebuild",
                        "controversiality": 0,
                        "depth": 0,
                        "author_flair_background_color": "",
                        "collapsed_because_crowd_control": null,
                        "mod_reports": [],
                        "num_reports": null,
                        "ups": 3
                    }
                },
                {
                    "kind": "t1",
                    "data": {
                        "subreddit_id": "t5_3bg30",
                        "approved_at_utc": null,
                        "author_is_blocked": false,
                        "comment_type": null,
                        "awarders": [],
                        "mod_reason_by": null,
                        "banned_by": null,
                        "author_flair_type": "text",
                        "total_awards_received": 0,
                        "subreddit": "Freebuild",
                        "author_flair_template_id": null,
                        "likes": null,
                        "replies": {
                            "kind": "Listing",
                            "data": {
                                "after": null,
                                "dist": null,
                                "modhash": "",
                                "geo_filter": "",
                                "children": [
                                    {
                                        "kind": "t1",
                                        "data": {
                                            "subreddit_id": "t5_3bg30",
                                            "approved_at_utc": null,
                                            "author_is_blocked": false,
                                            "comment_type": null,
                                            "awarders": [],
                                            "mod_reason_by": null,
                                            "banned_by": null,
                                            "author_flair_type": "text",
                                            "total_awards_received": 0,
                                            "subreddit": "Freebuild",
                                            "author_flair_template_id": null,
                                            "likes": null,
                                            "replies": "",
                                            "user_reports": [],
                                            "saved": false,
                                            "id": "dhy8ixu",
                                            "banned_at_utc": null,
                                            "mod_reason_title": null,
                                            "gilded": 0,
                                            "archived": false,
                                            "collapsed_reason_code": null,
                                            "no_follow": true,
                                            "author": "Zoocanadanda",
                                            "can_mod_post": false,
                                            "created_utc": 1495578034.0,
                                            "send_replies": true,
                                            "parent_id": "t1_dhy7o0e",
                                            "score": 2,
                                            "author_fullname": "t2_hsaxm",
                                            "removal_reason": null,
                                            "approved_by": null,
                                            "mod_note": null,
                                            "all_awardings": [],
                                            "body": "o7 to that",
                                            "edited": false,
                                            "top_awarded_type": null,
                                            "author_flair_css_class": null,
                                            "name": "t1_dhy8ixu",
                                            "is_submitter": true,
                                            "downs": 0,
                                            "author_flair_richtext": [],
                                            "author_patreon_flair": false,
                                            "body_html": "&lt;div class=\"md\"&gt;&lt;p&gt;o7 to that&lt;/p&gt;\n&lt;/div&gt;",
                                            "gildings": {},
                                            "collapsed_reason": null,
                                            "distinguished": null,
                                            "associated_award": null,
                                            "stickied": false,
                                            "author_premium": false,
                                            "can_gild": false,
                                            "link_id": "t3_6cxg3k",
                                            "unrepliable_reason": null,
                                            "author_flair_text_color": "dark",
                                            "score_hidden": false,
                                            "permalink": "/r/Freebuild/comments/6cxg3k/crisis_adverted_kekkekkekkekk_identity_revealed/dhy8ixu/",
                                            "subreddit_type": "public",
                                            "locked": false,
                                            "report_reasons": null,
                                            "created": 1495578034.0,
                                            "author_flair_text": "T.B.C",
                                            "treatment_tags": [],
                                            "collapsed": false,
                                            "subreddit_name_prefixed": "r/Freebuild",
                                            "controversiality": 0,
                                            "depth": 1,
                                            "author_flair_background_color": "",
                                            "collapsed_because_crowd_control": null,
                                            "mod_reports": [],
                                            "num_reports": null,
                                            "ups": 2
                                        }
                                    }
                                ],
                                "before": null
                            }
                        },
                        "user_reports": [],
                        "saved": false,
                        "id": "dhy7o0e",
                        "banned_at_utc": null,
                        "mod_reason_title": null,
                        "gilded": 0,
                        "archived": false,
                        "collapsed_reason_code": null,
                        "no_follow": false,
                        "author": "Stickman278",
                        "can_mod_post": false,
                        "created_utc": 1495576945.0,
                        "send_replies": true,
                        "parent_id": "t3_6cxg3k",
                        "score": 5,
                        "author_fullname": "t2_fcx9x",
                        "approved_by": null,
                        "mod_note": null,
                        "all_awardings": [],
                        "collapsed": false,
                        "body": "from someone who is known as kinda chill,\n\nPres is a shitty person.",
                        "edited": false,
                        "top_awarded_type": null,
                        "author_flair_css_class": null,
                        "name": "t1_dhy7o0e",
                        "is_submitter": false,
                        "downs": 0,
                        "author_flair_richtext": [],
                        "author_patreon_flair": false,
                        "body_html": "&lt;div class=\"md\"&gt;&lt;p&gt;from someone who is known as kinda chill,&lt;/p&gt;\n\n&lt;p&gt;Pres is a shitty person.&lt;/p&gt;\n&lt;/div&gt;",
                        "removal_reason": null,
                        "collapsed_reason": null,
                        "distinguished": null,
                        "associated_award": null,
                        "stickied": false,
                        "author_premium": false,
                        "can_gild": false,
                        "gildings": {},
                        "unrepliable_reason": null,
                        "author_flair_text_color": null,
                        "score_hidden": false,
                        "permalink": "/r/Freebuild/comments/6cxg3k/crisis_adverted_kekkekkekkekk_identity_revealed/dhy7o0e/",
                        "subreddit_type": "public",
                        "locked": false,
                        "report_reasons": null,
                        "created": 1495576945.0,
                        "author_flair_text": null,
                        "treatment_tags": [],
                        "link_id": "t3_6cxg3k",
                        "subreddit_name_prefixed": "r/Freebuild",
                        "controversiality": 0,
                        "depth": 0,
                        "author_flair_background_color": null,
                        "collapsed_because_crowd_control": null,
                        "mod_reports": [],
                        "num_reports": null,
                        "ups": 5
                    }
                },
                {
                    "kind": "t1",
                    "data": {
                        "total_awards_received": 0,
                        "approved_at_utc": null,
                        "author_is_blocked": false,
                        "comment_type": null,
                        "awarders": [],
                        "mod_reason_by": null,
                        "banned_by": null,
                        "ups": 3,
                        "removal_reason": null,
                        "link_id": "t3_6cxg3k",
                        "author_flair_template_id": null,
                        "likes": null,
                        "replies": "",
                        "user_reports": [],
                        "saved": false,
                        "id": "dhymeb0",
                        "banned_at_utc": null,
                        "mod_reason_title": null,
                        "gilded": 0,
                        "archived": false,
                        "collapsed_reason_code": null,
                        "no_follow": true,
                        "author": "[deleted]",
                        "can_mod_post": false,
                        "send_replies": true,
                        "parent_id": "t3_6cxg3k",
                        "score": 3,
                        "approved_by": null,
                        "report_reasons": null,
                        "all_awardings": [],
                        "subreddit_id": "t5_3bg30",
                        "body": "The great bamboozling of 2k17",
                        "edited": false,
                        "downs": 0,
                        "author_flair_css_class": null,
                        "collapsed": false,
                        "is_submitter": false,
                        "body_html": "&lt;div class=\"md\"&gt;&lt;p&gt;The great bamboozling of 2k17&lt;/p&gt;\n&lt;/div&gt;",
                        "gildings": {},
                        "collapsed_reason": null,
                        "associated_award": null,
                        "stickied": false,
                        "subreddit_type": "public",
                        "can_gild": false,
                        "top_awarded_type": null,
                        "unrepliable_reason": null,
                        "author_flair_text_color": "dark",
                        "score_hidden": false,
                        "permalink": "/r/Freebuild/comments/6cxg3k/crisis_adverted_kekkekkekkekk_identity_revealed/dhymeb0/",
                        "num_reports": null,
                        "locked": false,
                        "name": "t1_dhymeb0",
                        "created": 1495595205.0,
                        "subreddit": "Freebuild",
                        "author_flair_text": null,
                        "treatment_tags": [],
                        "created_utc": 1495595205.0,
                        "subreddit_name_prefixed": "r/Freebuild",
                        "controversiality": 0,
                        "depth": 0,
                        "author_flair_background_color": "",
                        "collapsed_because_crowd_control": null,
                        "mod_reports": [],
                        "mod_note": null,
                        "distinguished": null
                    }
                },
                {
                    "kind": "t1",
                    "data": {
                        "subreddit_id": "t5_3bg30",
                        "approved_at_utc": null,
                        "author_is_blocked": false,
                        "comment_type": null,
                        "awarders": [],
                        "mod_reason_by": null,
                        "banned_by": null,
                        "author_flair_type": "text",
                        "total_awards_received": 0,
                        "subreddit": "Freebuild",
                        "author_flair_template_id": null,
                        "likes": null,
                        "replies": "",
                        "user_reports": [],
                        "saved": false,
                        "id": "dhy4czm",
                        "banned_at_utc": null,
                        "mod_reason_title": null,
                        "gilded": 0,
                        "archived": false,
                        "collapsed_reason_code": null,
                        "no_follow": true,
                        "author": "DrydonTheAlt",
                        "can_mod_post": false,
                        "created_utc": 1495573039.0,
                        "send_replies": true,
                        "parent_id": "t3_6cxg3k",
                        "score": 2,
                        "author_fullname": "t2_y6opy",
                        "approved_by": null,
                        "mod_note": null,
                        "all_awardings": [],
                        "collapsed": false,
                        "body": "ahem\n\n\n\n\n\n\n\n\n\n\n\n\n\n\n\n\n\n\n\n\n\nfuck pres for doing this",
                        "edited": false,
                        "top_awarded_type": null,
                        "author_flair_css_class": "",
                        "name": "t1_dhy4czm",
                        "is_submitter": false,
                        "downs": 0,
                        "author_flair_richtext": [],
                        "author_patreon_flair": false,
                        "body_html": "&lt;div class=\"md\"&gt;&lt;p&gt;ahem&lt;/p&gt;\n\n&lt;p&gt;fuck pres for doing this&lt;/p&gt;\n&lt;/div&gt;",
                        "removal_reason": null,
                        "collapsed_reason": null,
                        "distinguished": null,
                        "associated_award": null,
                        "stickied": false,
                        "author_premium": false,
                        "can_gild": false,
                        "gildings": {},
                        "unrepliable_reason": null,
                        "author_flair_text_color": "dark",
                        "score_hidden": false,
                        "permalink": "/r/Freebuild/comments/6cxg3k/crisis_adverted_kekkekkekkekk_identity_revealed/dhy4czm/",
                        "subreddit_type": "public",
                        "locked": false,
                        "report_reasons": null,
                        "created": 1495573039.0,
                        "author_flair_text": "Oldfag",
                        "treatment_tags": [],
                        "link_id": "t3_6cxg3k",
                        "subreddit_name_prefixed": "r/Freebuild",
                        "controversiality": 0,
                        "depth": 0,
                        "author_flair_background_color": "",
                        "collapsed_because_crowd_control": null,
                        "mod_reports": [],
                        "num_reports": null,
                        "ups": 2
                    }
                },
                {
                    "kind": "t1",
                    "data": {
                        "subreddit_id": "t5_3bg30",
                        "approved_at_utc": null,
                        "author_is_blocked": false,
                        "comment_type": null,
                        "awarders": [],
                        "mod_reason_by": null,
                        "banned_by": null,
                        "author_flair_type": "text",
                        "total_awards_received": 0,
                        "subreddit": "Freebuild",
                        "author_flair_template_id": null,
                        "likes": null,
                        "replies": "",
                        "user_reports": [],
                        "saved": false,
                        "id": "dhy4zpx",
                        "banned_at_utc": null,
                        "mod_reason_title": null,
                        "gilded": 0,
                        "archived": false,
                        "collapsed_reason_code": null,
                        "no_follow": true,
                        "author": "king_ass_man",
                        "can_mod_post": false,
                        "created_utc": 1495573759.0,
                        "send_replies": true,
                        "parent_id": "t3_6cxg3k",
                        "score": 2,
                        "author_fullname": "t2_135wpi",
                        "approved_by": null,
                        "mod_note": null,
                        "all_awardings": [],
                        "collapsed": false,
                        "body": "ahahahahahahahahahahahahahahahahahahahahahahahahahahahahahahahahahahahahahahahaha",
                        "edited": false,
                        "top_awarded_type": null,
                        "author_flair_css_class": null,
                        "name": "t1_dhy4zpx",
                        "is_submitter": false,
                        "downs": 0,
                        "author_flair_richtext": [],
                        "author_patreon_flair": false,
                        "body_html": "&lt;div class=\"md\"&gt;&lt;p&gt;ahahahahahahahahahahahahahahahahahahahahahahahahahahahahahahahahahahahahahahahaha&lt;/p&gt;\n&lt;/div&gt;",
                        "removal_reason": null,
                        "collapsed_reason": null,
                        "distinguished": null,
                        "associated_award": null,
                        "stickied": false,
                        "author_premium": false,
                        "can_gild": false,
                        "gildings": {},
                        "unrepliable_reason": null,
                        "author_flair_text_color": null,
                        "score_hidden": false,
                        "permalink": "/r/Freebuild/comments/6cxg3k/crisis_adverted_kekkekkekkekk_identity_revealed/dhy4zpx/",
                        "subreddit_type": "public",
                        "locked": false,
                        "report_reasons": null,
                        "created": 1495573759.0,
                        "author_flair_text": null,
                        "treatment_tags": [],
                        "link_id": "t3_6cxg3k",
                        "subreddit_name_prefixed": "r/Freebuild",
                        "controversiality": 0,
                        "depth": 0,
                        "author_flair_background_color": null,
                        "collapsed_because_crowd_control": null,
                        "mod_reports": [],
                        "num_reports": null,
                        "ups": 2
                    }
                },
                {
                    "kind": "t1",
                    "data": {
                        "total_awards_received": 0,
                        "approved_at_utc": null,
                        "author_is_blocked": false,
                        "comment_type": null,
                        "awarders": [],
                        "mod_reason_by": null,
                        "banned_by": null,
                        "ups": 2,
                        "removal_reason": null,
                        "link_id": "t3_6cxg3k",
                        "author_flair_template_id": null,
                        "likes": null,
                        "replies": "",
                        "user_reports": [],
                        "saved": false,
                        "id": "dhy5u16",
                        "banned_at_utc": null,
                        "mod_reason_title": null,
                        "gilded": 0,
                        "archived": false,
                        "collapsed_reason_code": null,
                        "no_follow": true,
                        "author": "[deleted]",
                        "can_mod_post": false,
                        "send_replies": true,
                        "parent_id": "t3_6cxg3k",
                        "score": 2,
                        "approved_by": null,
                        "report_reasons": null,
                        "all_awardings": [],
                        "subreddit_id": "t5_3bg30",
                        "body": "CALLED IT",
                        "edited": 1495575411.0,
                        "downs": 0,
                        "author_flair_css_class": null,
                        "collapsed": false,
                        "is_submitter": false,
                        "body_html": "&lt;div class=\"md\"&gt;&lt;p&gt;CALLED IT&lt;/p&gt;\n&lt;/div&gt;",
                        "gildings": {},
                        "collapsed_reason": null,
                        "associated_award": null,
                        "stickied": false,
                        "subreddit_type": "public",
                        "can_gild": false,
                        "top_awarded_type": null,
                        "unrepliable_reason": null,
                        "author_flair_text_color": "dark",
                        "score_hidden": false,
                        "permalink": "/r/Freebuild/comments/6cxg3k/crisis_adverted_kekkekkekkekk_identity_revealed/dhy5u16/",
                        "num_reports": null,
                        "locked": false,
                        "name": "t1_dhy5u16",
                        "created": 1495574742.0,
                        "subreddit": "Freebuild",
                        "author_flair_text": null,
                        "treatment_tags": [],
                        "created_utc": 1495574742.0,
                        "subreddit_name_prefixed": "r/Freebuild",
                        "controversiality": 0,
                        "depth": 0,
                        "author_flair_background_color": "",
                        "collapsed_because_crowd_control": null,
                        "mod_reports": [],
                        "mod_note": null,
                        "distinguished": null
                    }
                },
                {
                    "kind": "t1",
                    "data": {
                        "subreddit_id": "t5_3bg30",
                        "approved_at_utc": null,
                        "author_is_blocked": false,
                        "comment_type": null,
                        "awarders": [],
                        "mod_reason_by": null,
                        "banned_by": null,
                        "author_flair_type": "text",
                        "total_awards_received": 0,
                        "subreddit": "Freebuild",
                        "author_flair_template_id": null,
                        "likes": null,
                        "replies": "",
                        "user_reports": [],
                        "saved": false,
                        "id": "dhy4gsm",
                        "banned_at_utc": null,
                        "mod_reason_title": null,
                        "gilded": 0,
                        "archived": false,
                        "collapsed_reason_code": null,
                        "no_follow": true,
                        "author": "ThatReddittor",
                        "can_mod_post": false,
                        "created_utc": 1495573157.0,
                        "send_replies": true,
                        "parent_id": "t3_6cxg3k",
                        "score": 1,
                        "author_fullname": "t2_licb5",
                        "approved_by": null,
                        "mod_note": null,
                        "all_awardings": [],
                        "collapsed": false,
                        "body": "I cant believe I forgave the little piece of shit. Has his kekekekkek account been reported to reddit admins?",
                        "edited": false,
                        "top_awarded_type": null,
                        "author_flair_css_class": "",
                        "name": "t1_dhy4gsm",
                        "is_submitter": false,
                        "downs": 0,
                        "author_flair_richtext": [],
                        "author_patreon_flair": false,
                        "body_html": "&lt;div class=\"md\"&gt;&lt;p&gt;I cant believe I forgave the little piece of shit. Has his kekekekkek account been reported to reddit admins?&lt;/p&gt;\n&lt;/div&gt;",
                        "removal_reason": null,
                        "collapsed_reason": null,
                        "distinguished": null,
                        "associated_award": null,
                        "stickied": false,
                        "author_premium": false,
                        "can_gild": false,
                        "gildings": {},
                        "unrepliable_reason": null,
                        "author_flair_text_color": "dark",
                        "score_hidden": false,
                        "permalink": "/r/Freebuild/comments/6cxg3k/crisis_adverted_kekkekkekkekk_identity_revealed/dhy4gsm/",
                        "subreddit_type": "public",
                        "locked": false,
                        "report_reasons": null,
                        "created": 1495573157.0,
                        "author_flair_text": "SALT",
                        "treatment_tags": [],
                        "link_id": "t3_6cxg3k",
                        "subreddit_name_prefixed": "r/Freebuild",
                        "controversiality": 0,
                        "depth": 0,
                        "author_flair_background_color": "",
                        "collapsed_because_crowd_control": null,
                        "mod_reports": [],
                        "num_reports": null,
                        "ups": 1
                    }
                }
            ],
            "before": null
        }
    }
]